setup.py
chinesePdfLaTex/LaTexCommand.py
chinesePdfLaTex/__init__.py
chinesePdfLaTex/chineseCom.py
chinesePdfLaTex/chineseIndex.py
chinesePdfLaTex/chinesePdfLaTex.py
chinesePdfLaTex/logger.py
chinesePdfLaTex.egg-info/PKG-INFO
chinesePdfLaTex.egg-info/SOURCES.txt
chinesePdfLaTex.egg-info/dependency_links.txt
chinesePdfLaTex.egg-info/top_level.txt
chinesePdfLaTex/test/__init__.py
chinesePdfLaTex/test/indexTest.py
chinesePdfLaTex/test/latexTest.py
chinesePdfLaTex/test/mainTest.py