Metadata-Version: 1.0
Name: chinesePdfLaTex
Version: 1.0.7
Summary: chinese index and book mard with pdflatex tool
Home-page: http://wizard.ren
Author: yangjie
Author-email: chnyangjie@163.com
License: Free
Keywords: chinese,pdflatex,index,bookmark
Platform: any
